pytest_tf/__init__.py
pytest_tf/exception.py
pytest_tf/main.py
pytest_tf/markers.py
pytest_tf/plugin.py
pytest_tf/runner.py
pytest_tf-0.1.0.dist-info/LICENSE
pytest_tf-0.1.0.dist-info/METADATA
pytest_tf-0.1.0.dist-info/WHEEL
pytest_tf-0.1.0.dist-info/entry_points.txt
pytest_tf-0.1.0.dist-info/RECORD
