Metadata-Version: 2.1
Name: pytest-tf
Version: 0.1.0
Summary: Test your OpenTofu and Terraform config using a PyTest plugin
License: MIT
Author: Adrian Covaci
Author-email: adrian.covaci@oaknorth.co.uk
Requires-Python: >=3.12,<4.0
Classifier: License :: OSI Approved :: MIT License
Classifier: Programming Language :: Python :: 3
Classifier: Programming Language :: Python :: 3.12
Requires-Dist: black (>=24.4.2,<25.0.0)
Requires-Dist: pytest (>=8.2.1,<9.0.0)
Requires-Dist: sh (>=2.0.6,<3.0.0)
